PySwitchCase/__init__.py
PySwitchCase/__version__.py
PySwitchCase/examples.py
PySwitchCase/switcher.py
PySwitchCase-1.0.2.dist-info/LICENSE
PySwitchCase-1.0.2.dist-info/METADATA
PySwitchCase-1.0.2.dist-info/WHEEL
PySwitchCase-1.0.2.dist-info/top_level.txt
PySwitchCase-1.0.2.dist-info/RECORD
